setup.py
pyrainyday/__init__.py
pyrainyday/pyrainyday.py
pyrainyday.egg-info/PKG-INFO
pyrainyday.egg-info/SOURCES.txt
pyrainyday.egg-info/dependency_links.txt
pyrainyday.egg-info/requires.txt
pyrainyday.egg-info/top_level.txt