Metadata-Version: 2.1
Name: pyrainyday
Version: 1.0.0
Summary: Weather Forecast Data
Home-page: https://github.com/Savn55/Package/tree/main/weather_forecast
Author: Sabin Bhujel
Author-email: sabinvhujel55@gmail.com
License: MIT
Keywords: weather,forecast,openweather
Platform: UNKNOWN
Classifier: Development Status :: 4 - Beta
Classifier: Intended Audience :: Developers
Classifier: Operating System :: MacOS :: MacOS X
Classifier: Operating System :: Microsoft :: Windows
Classifier: Programming Language :: Python :: 3.5
Classifier: Programming Language :: Python :: 3.6
Classifier: Programming Language :: Python :: 3.7
Classifier: Programming Language :: Python :: 3.8
Classifier: Programming Language :: Python :: 3.9
